sqalp/__init__.py
sqalp/sqalp.py
sqalp-1.2.0.dev0.dist-info/DESCRIPTION.rst
sqalp-1.2.0.dev0.dist-info/METADATA
sqalp-1.2.0.dev0.dist-info/RECORD
sqalp-1.2.0.dev0.dist-info/WHEEL
sqalp-1.2.0.dev0.dist-info/entry_points.txt
sqalp-1.2.0.dev0.dist-info/metadata.json
sqalp-1.2.0.dev0.dist-info/top_level.txt
