Metadata-Version: 2.0
Name: sqalp
Version: 1.2.0.dev0
Summary: Apache log parser
Home-page: https://github.com/bedge/sqalp
Author: Bruce Edge
Author-email: bruce.edge@gmail.com
License: UNKNOWN
Project-URL: Bug Reports, https://github.com/bedge/sqalp/issues
Project-URL: Funding, https://donate.pypi.org
Project-URL: Source, https://github.com/bedge/sqalp/
Keywords: apache log parser
Platform: UNKNOWN
Classifier: Development Status :: 3 - Alpha
Classifier: Intended Audience :: Developers
Classifier: Environment :: Console
Classifier: Topic :: Text Processing :: Filters
Classifier: License :: OSI Approved :: MIT License
Classifier: Programming Language :: Python :: 3.6
Requires-Python: >=3.6
Provides-Extra: dev
Provides-Extra: test
Requires-Dist: apache-log-parser
Requires-Dist: sqlalchemy
Requires-Dist: tabulate
Requires-Dist: pyyaml
Requires-Dist: ua-parser
Requires-Dist: user-agents
Requires-Dist: typing
Requires-Dist: pyannotate
Provides-Extra: dev
Requires-Dist: check-manifest; extra == 'dev'
Provides-Extra: test
Requires-Dist: coverage; extra == 'test'
